[
  {
    "number": "151",
    "name": "Gunilla Persdotter",
    "relationship": "1",
    "suffix": ", född 1751-06-28 i Sollefteå bruk, Sollefteå sn,  död 1813-06-03 i Västergranvåg, Sollefteå sn."
  },
  {
    "number": "302",
    "name": "Per Ersson",
    "relationship": "f",
    "suffix": ", född 1707, död 1789-02-11 i Sollefteå bruk, Sollefteå sn.  Dagverkskarl i Sollefteå bruk, Sollefteå sn."
  },
  {
    "number": "303",
    "name": "Maria Andersdotter",
    "relationship": "m",
    "suffix": ", född 1711-01-05 i Golva, Boteå sn, död 1777-01-26  i Sollefteå bruk, Sollefteå sn."
  }
]